odoo9_addon_partner_firstname-9.0.2.0.0.99.dev8-py3.8-nspkg.pth
odoo_addons/partner_firstname/README.rst
odoo_addons/partner_firstname/__init__.py
odoo_addons/partner_firstname/__openerp__.py
odoo_addons/partner_firstname/exceptions.py
odoo_addons/partner_firstname/data/res_partner.yml
odoo_addons/partner_firstname/i18n/am.po
odoo_addons/partner_firstname/i18n/ar.po
odoo_addons/partner_firstname/i18n/bg.po
odoo_addons/partner_firstname/i18n/bs.po
odoo_addons/partner_firstname/i18n/ca.po
odoo_addons/partner_firstname/i18n/cs.po
odoo_addons/partner_firstname/i18n/da.po
odoo_addons/partner_firstname/i18n/de.po
odoo_addons/partner_firstname/i18n/el_GR.po
odoo_addons/partner_firstname/i18n/en_GB.po
odoo_addons/partner_firstname/i18n/es.po
odoo_addons/partner_firstname/i18n/es_CR.po
odoo_addons/partner_firstname/i18n/es_EC.po
odoo_addons/partner_firstname/i18n/es_ES.po
odoo_addons/partner_firstname/i18n/es_MX.po
odoo_addons/partner_firstname/i18n/es_VE.po
odoo_addons/partner_firstname/i18n/et.po
odoo_addons/partner_firstname/i18n/eu.po
odoo_addons/partner_firstname/i18n/fi.po
odoo_addons/partner_firstname/i18n/fr.po
odoo_addons/partner_firstname/i18n/fr_CA.po
odoo_addons/partner_firstname/i18n/fr_CH.po
odoo_addons/partner_firstname/i18n/gl.po
odoo_addons/partner_firstname/i18n/hr.po
odoo_addons/partner_firstname/i18n/hr_HR.po
odoo_addons/partner_firstname/i18n/hu.po
odoo_addons/partner_firstname/i18n/id.po
odoo_addons/partner_firstname/i18n/it.po
odoo_addons/partner_firstname/i18n/ja.po
odoo_addons/partner_firstname/i18n/lt.po
odoo_addons/partner_firstname/i18n/lv.po
odoo_addons/partner_firstname/i18n/mk.po
odoo_addons/partner_firstname/i18n/mn.po
odoo_addons/partner_firstname/i18n/nb.po
odoo_addons/partner_firstname/i18n/nb_NO.po
odoo_addons/partner_firstname/i18n/nl.po
odoo_addons/partner_firstname/i18n/nl_BE.po
odoo_addons/partner_firstname/i18n/partner_firstname.pot
odoo_addons/partner_firstname/i18n/pl.po
odoo_addons/partner_firstname/i18n/pt.po
odoo9_addon_partner_firstname-9.0.2.0.0.99.dev8.dist-info/METADATA
odoo9_addon_partner_firstname-9.0.2.0.0.99.dev8.dist-info/WHEEL
odoo9_addon_partner_firstname-9.0.2.0.0.99.dev8.dist-info/namespace_packages.txt
odoo9_addon_partner_firstname-9.0.2.0.0.99.dev8.dist-info/top_level.txt
odoo9_addon_partner_firstname-9.0.2.0.0.99.dev8.dist-info/RECORD
